pytorch_lr_tuner/__init__.py
pytorch_lr_tuner/lr_finder.py
pytorch_lr_tuner-0.0.2.dist-info/LICENSE
pytorch_lr_tuner-0.0.2.dist-info/METADATA
pytorch_lr_tuner-0.0.2.dist-info/WHEEL
pytorch_lr_tuner-0.0.2.dist-info/top_level.txt
pytorch_lr_tuner-0.0.2.dist-info/RECORD
