Metadata-Version: 2.1
Name: pytorch-lr-tuner
Version: 0.0.2
Summary: Optimum learning rate finder for PyTorch Models
Home-page: https://github.com/Therap-ML/pytorch-lr-tuner
Author: Saif Mahmud
Author-email: saif.dhrubo@gmail.com
License: UNKNOWN
Platform: UNKNOWN
Classifier: Programming Language :: Python :: 3
Classifier: License :: OSI Approved :: MIT License
Classifier: Operating System :: OS Independent
Requires-Python: >=3.6
